AUTHORS
CHANGES.txt
INSTALL
LICENSE
MANIFEST.in
README.rst
setup.cfg
setup.py
setup_utils.py
acris/VERSION.py
acris/__init__.py
acris.egg-info/PKG-INFO
acris.egg-info/SOURCES.txt
acris.egg-info/dependency_links.txt
acris.egg-info/requires.txt
acris.egg-info/top_level.txt
acris/idioms/__init__.py
acris/idioms/cluster_resource_pool.py
acris/idioms/resource_pool.py
acris/idioms/virtual_resource_pool.py
acris/idioms/virtual_resource_pool_db.py
acris/misc/__init__.py
acris/misc/case_style.py
acris/misc/msort.py
acris/misc/xlsx2rst.py
acris/osutils/__init__.py
acris/osutils/bee.py
acris/osutils/commdir.py
acris/osutils/csv2xlsx.py
acris/osutils/hive.py
acris/osutils/mail.py
acris/osutils/misc.py
acris/osutils/mrun.py
acris/osutils/prettyxml.py