Metadata-Version: 1.1
Name: acris
Version: 3.0.4
Summary: acris is a python library of programming patterns that we use, at acrisel, in Python projects and choose to contribute to Python community
Home-page: https://github.com/Acrisel/acris
Author: Acrisel Team
Author-email: support@acrisel.com
License: MIT
Keywords: library sequence logger yield singleton thread synchronize resource pool utilities os ssh xml excel mail
Platform: UNKNOWN
Classifier: Development Status :: 5 - Production/Stable
Classifier: Environment :: Other Environment
Classifier: Intended Audience :: Developers
Classifier: License :: OSI Approved :: MIT License
Classifier: Operating System :: OS Independent
Classifier: Programming Language :: Python
Classifier: Programming Language :: Python :: 3
Classifier: Topic :: Software Development :: Libraries :: Application Frameworks
Classifier: Topic :: Software Development :: Libraries :: Python Modules
